smart_cloud_tag/__init__.py
smart_cloud_tag/config.py
smart_cloud_tag/core.py
smart_cloud_tag/exceptions.py
smart_cloud_tag/models.py
smart_cloud_tag/schemas.py
smart_cloud_tag/utils.py
smart_cloud_tag/llm/__init__.py
smart_cloud_tag/llm/anthropic_provider.py
smart_cloud_tag/llm/base.py
smart_cloud_tag/llm/gemini_provider.py
smart_cloud_tag/llm/openai_provider.py
smart_cloud_tag/providers/__init__.py
smart_cloud_tag/providers/aws_s3.py
smart_cloud_tag/providers/azure_blob.py
smart_cloud_tag/providers/base.py
smart_cloud_tag/providers/gcs_provider.py
smart_cloud_tag-0.1.2.dist-info/METADATA
smart_cloud_tag-0.1.2.dist-info/WHEEL
smart_cloud_tag-0.1.2.dist-info/licenses/LICENSE
smart_cloud_tag-0.1.2.dist-info/RECORD
