Metadata-Version: 2.4
Name: smart_cloud_tag
Version: 0.1.2
Summary: AI-powered cloud storage object tagging using LLMs
Project-URL: Homepage, https://github.com/DawarWaqar/smart_cloud_tag
Project-URL: Repository, https://github.com/DawarWaqar/smart_cloud_tag
Project-URL: Issues, https://github.com/DawarWaqar/smart_cloud_tag/issues
Author-email: Dawar Waqar <dawarwaqar71@gmail.com>
License: MIT
License-File: LICENSE
Keywords: anthropic,aws,azure,cloud-storage,gcp,gemini,llm,openai,s3,tagging
Classifier: Development Status :: 3 - Alpha
Classifier: Intended Audience :: Developers
Classifier: License :: OSI Approved :: MIT License
Classifier: Programming Language :: Python :: 3
Classifier: Programming Language :: Python :: 3.8
Classifier: Programming Language :: Python :: 3.9
Classifier: Programming Language :: Python :: 3.10
Classifier: Programming Language :: Python :: 3.11
Classifier: Programming Language :: Python :: 3.12
Classifier: Topic :: Scientific/Engineering :: Artificial Intelligence
Classifier: Topic :: Software Development :: Libraries :: Python Modules
Classifier: Topic :: System :: Filesystems
Classifier: Topic :: Text Processing :: Linguistic
Requires-Python: >=3.8
Requires-Dist: boto3>=1.26.0
Requires-Dist: openai>=1.0.0
Requires-Dist: pydantic>=2.0.0
Requires-Dist: python-dotenv>=1.0.0
Requires-Dist: python-magic>=0.4.27
Provides-Extra: all
Requires-Dist: anthropic>=0.7.0; extra == 'all'
Requires-Dist: async-timeout>=4.0.0; extra == 'all'
Requires-Dist: azure-storage-blob>=12.0.0; extra == 'all'
Requires-Dist: google-cloud-storage>=2.0.0; extra == 'all'
Requires-Dist: google-generativeai>=0.3.0; extra == 'all'
Provides-Extra: anthropic
Requires-Dist: anthropic>=0.7.0; extra == 'anthropic'
Provides-Extra: aws
Requires-Dist: boto3>=1.26.0; extra == 'aws'
Provides-Extra: azure
Requires-Dist: azure-storage-blob>=12.0.0; extra == 'azure'
Provides-Extra: dev
Requires-Dist: black>=23.0.0; extra == 'dev'
Requires-Dist: isort>=5.12.0; extra == 'dev'
Requires-Dist: mypy>=1.0.0; extra == 'dev'
Requires-Dist: pytest-cov>=4.0.0; extra == 'dev'
Requires-Dist: pytest>=7.0.0; extra == 'dev'
Requires-Dist: ruff>=0.1.0; extra == 'dev'
Provides-Extra: gcp
Requires-Dist: google-cloud-storage>=2.0.0; extra == 'gcp'
Provides-Extra: gemini
Requires-Dist: async-timeout>=4.0.0; extra == 'gemini'
Requires-Dist: google-generativeai>=0.3.0; extra == 'gemini'
Provides-Extra: openai
Requires-Dist: openai>=1.0.0; extra == 'openai'
